package android.support.v7.widget;

import android.content.Context;
import android.graphics.drawable.Drawable;
import android.os.Build;
import android.support.v7.b.a;
import android.util.AttributeSet;
import android.view.ActionMode;
import android.view.MotionEvent;
import android.view.View;
import android.view.ViewGroup;
import android.widget.FrameLayout;

public class ActionBarContainer extends FrameLayout {
  Drawable a;
  
  Drawable b;
  
  Drawable c;
  
  boolean d;
  
  boolean e;
  
  private boolean f;
  
  private View g;
  
  private View h;
  
  private View i;
  
  private int j;
  
  public ActionBarContainer(Context paramContext) { this(paramContext, null); }
  
  public ActionBarContainer(Context paramContext, AttributeSet paramAttributeSet) { // Byte code:
    //   0: aload_0
    //   1: aload_1
    //   2: aload_2
    //   3: invokespecial <init> : (Landroid/content/Context;Landroid/util/AttributeSet;)V
    //   6: getstatic android/os/Build$VERSION.SDK_INT : I
    //   9: bipush #21
    //   11: if_icmplt -> 26
    //   14: new android/support/v7/widget/c
    //   17: dup
    //   18: aload_0
    //   19: invokespecial <init> : (Landroid/support/v7/widget/ActionBarContainer;)V
    //   22: astore_3
    //   23: goto -> 35
    //   26: new android/support/v7/widget/b
    //   29: dup
    //   30: aload_0
    //   31: invokespecial <init> : (Landroid/support/v7/widget/ActionBarContainer;)V
    //   34: astore_3
    //   35: aload_0
    //   36: aload_3
    //   37: invokevirtual setBackgroundDrawable : (Landroid/graphics/drawable/Drawable;)V
    //   40: aload_1
    //   41: aload_2
    //   42: getstatic android/support/v7/b/a$k.ActionBar : [I
    //   45: invokevirtual obtainStyledAttributes : (Landroid/util/AttributeSet;[I)Landroid/content/res/TypedArray;
    //   48: astore_1
    //   49: aload_0
    //   50: aload_1
    //   51: getstatic android/support/v7/b/a$k.ActionBar_background : I
    //   54: invokevirtual getDrawable : (I)Landroid/graphics/drawable/Drawable;
    //   57: putfield a : Landroid/graphics/drawable/Drawable;
    //   60: aload_0
    //   61: aload_1
    //   62: getstatic android/support/v7/b/a$k.ActionBar_backgroundStacked : I
    //   65: invokevirtual getDrawable : (I)Landroid/graphics/drawable/Drawable;
    //   68: putfield b : Landroid/graphics/drawable/Drawable;
    //   71: aload_0
    //   72: aload_1
    //   73: getstatic android/support/v7/b/a$k.ActionBar_height : I
    //   76: iconst_m1
    //   77: invokevirtual getDimensionPixelSize : (II)I
    //   80: putfield j : I
    //   83: aload_0
    //   84: invokevirtual getId : ()I
    //   87: getstatic android/support/v7/b/a$f.split_action_bar : I
    //   90: if_icmpne -> 109
    //   93: aload_0
    //   94: iconst_1
    //   95: putfield d : Z
    //   98: aload_0
    //   99: aload_1
    //   100: getstatic android/support/v7/b/a$k.ActionBar_backgroundSplit : I
    //   103: invokevirtual getDrawable : (I)Landroid/graphics/drawable/Drawable;
    //   106: putfield c : Landroid/graphics/drawable/Drawable;
    //   109: aload_1
    //   110: invokevirtual recycle : ()V
    //   113: aload_0
    //   114: getfield d : Z
    //   117: istore #4
    //   119: iconst_0
    //   120: istore #5
    //   122: iload #4
    //   124: ifeq -> 144
    //   127: iload #5
    //   129: istore #4
    //   131: aload_0
    //   132: getfield c : Landroid/graphics/drawable/Drawable;
    //   135: ifnonnull -> 169
    //   138: iconst_1
    //   139: istore #4
    //   141: goto -> 169
    //   144: iload #5
    //   146: istore #4
    //   148: aload_0
    //   149: getfield a : Landroid/graphics/drawable/Drawable;
    //   152: ifnonnull -> 169
    //   155: iload #5
    //   157: istore #4
    //   159: aload_0
    //   160: getfield b : Landroid/graphics/drawable/Drawable;
    //   163: ifnonnull -> 169
    //   166: goto -> 138
    //   169: aload_0
    //   170: iload #4
    //   172: invokevirtual setWillNotDraw : (Z)V
    //   175: return }
  
  private boolean a(View paramView) { return (paramView == null || paramView.getVisibility() == 8 || paramView.getMeasuredHeight() == 0); }
  
  private int b(View paramView) {
    FrameLayout.LayoutParams layoutParams = (FrameLayout.LayoutParams)paramView.getLayoutParams();
    return paramView.getMeasuredHeight() + layoutParams.topMargin + layoutParams.bottomMargin;
  }
  
  protected void drawableStateChanged() {
    super.drawableStateChanged();
    if (this.a != null && this.a.isStateful())
      this.a.setState(getDrawableState()); 
    if (this.b != null && this.b.isStateful())
      this.b.setState(getDrawableState()); 
    if (this.c != null && this.c.isStateful())
      this.c.setState(getDrawableState()); 
  }
  
  public View getTabContainer() { return this.g; }
  
  public void jumpDrawablesToCurrentState() {
    if (Build.VERSION.SDK_INT >= 11) {
      super.jumpDrawablesToCurrentState();
      if (this.a != null)
        this.a.jumpToCurrentState(); 
      if (this.b != null)
        this.b.jumpToCurrentState(); 
      if (this.c != null)
        this.c.jumpToCurrentState(); 
    } 
  }
  
  public void onFinishInflate() {
    super.onFinishInflate();
    this.h = findViewById(a.f.action_bar);
    this.i = findViewById(a.f.action_context_bar);
  }
  
  public boolean onInterceptTouchEvent(MotionEvent paramMotionEvent) { return (this.f || super.onInterceptTouchEvent(paramMotionEvent)); }
  
  public void onLayout(boolean paramBoolean, int paramInt1, int paramInt2, int paramInt3, int paramInt4) { // Byte code:
    //   0: aload_0
    //   1: iload_1
    //   2: iload_2
    //   3: iload_3
    //   4: iload #4
    //   6: iload #5
    //   8: invokespecial onLayout : (ZIIII)V
    //   11: aload_0
    //   12: getfield g : Landroid/view/View;
    //   15: astore #6
    //   17: iconst_1
    //   18: istore #5
    //   20: iconst_0
    //   21: istore_3
    //   22: aload #6
    //   24: ifnull -> 42
    //   27: aload #6
    //   29: invokevirtual getVisibility : ()I
    //   32: bipush #8
    //   34: if_icmpeq -> 42
    //   37: iconst_1
    //   38: istore_1
    //   39: goto -> 44
    //   42: iconst_0
    //   43: istore_1
    //   44: aload #6
    //   46: ifnull -> 105
    //   49: aload #6
    //   51: invokevirtual getVisibility : ()I
    //   54: bipush #8
    //   56: if_icmpeq -> 105
    //   59: aload_0
    //   60: invokevirtual getMeasuredHeight : ()I
    //   63: istore #7
    //   65: aload #6
    //   67: invokevirtual getLayoutParams : ()Landroid/view/ViewGroup$LayoutParams;
    //   70: checkcast android/widget/FrameLayout$LayoutParams
    //   73: astore #8
    //   75: aload #6
    //   77: iload_2
    //   78: iload #7
    //   80: aload #6
    //   82: invokevirtual getMeasuredHeight : ()I
    //   85: isub
    //   86: aload #8
    //   88: getfield bottomMargin : I
    //   91: isub
    //   92: iload #4
    //   94: iload #7
    //   96: aload #8
    //   98: getfield bottomMargin : I
    //   101: isub
    //   102: invokevirtual layout : (IIII)V
    //   105: aload_0
    //   106: getfield d : Z
    //   109: ifeq -> 147
    //   112: aload_0
    //   113: getfield c : Landroid/graphics/drawable/Drawable;
    //   116: ifnull -> 142
    //   119: aload_0
    //   120: getfield c : Landroid/graphics/drawable/Drawable;
    //   123: iconst_0
    //   124: iconst_0
    //   125: aload_0
    //   126: invokevirtual getMeasuredWidth : ()I
    //   129: aload_0
    //   130: invokevirtual getMeasuredHeight : ()I
    //   133: invokevirtual setBounds : (IIII)V
    //   136: iload #5
    //   138: istore_2
    //   139: goto -> 339
    //   142: iconst_0
    //   143: istore_2
    //   144: goto -> 339
    //   147: iload_3
    //   148: istore_2
    //   149: aload_0
    //   150: getfield a : Landroid/graphics/drawable/Drawable;
    //   153: ifnull -> 290
    //   156: aload_0
    //   157: getfield h : Landroid/view/View;
    //   160: invokevirtual getVisibility : ()I
    //   163: ifne -> 220
    //   166: aload_0
    //   167: getfield a : Landroid/graphics/drawable/Drawable;
    //   170: astore #8
    //   172: aload_0
    //   173: getfield h : Landroid/view/View;
    //   176: invokevirtual getLeft : ()I
    //   179: istore_2
    //   180: aload_0
    //   181: getfield h : Landroid/view/View;
    //   184: invokevirtual getTop : ()I
    //   187: istore #4
    //   189: aload_0
    //   190: getfield h : Landroid/view/View;
    //   193: invokevirtual getRight : ()I
    //   196: istore_3
    //   197: aload_0
    //   198: getfield h : Landroid/view/View;
    //   201: astore #9
    //   203: aload #8
    //   205: iload_2
    //   206: iload #4
    //   208: iload_3
    //   209: aload #9
    //   211: invokevirtual getBottom : ()I
    //   214: invokevirtual setBounds : (IIII)V
    //   217: goto -> 288
    //   220: aload_0
    //   221: getfield i : Landroid/view/View;
    //   224: ifnull -> 277
    //   227: aload_0
    //   228: getfield i : Landroid/view/View;
    //   231: invokevirtual getVisibility : ()I
    //   234: ifne -> 277
    //   237: aload_0
    //   238: getfield a : Landroid/graphics/drawable/Drawable;
    //   241: astore #8
    //   243: aload_0
    //   244: getfield i : Landroid/view/View;
    //   247: invokevirtual getLeft : ()I
    //   250: istore_2
    //   251: aload_0
    //   252: getfield i : Landroid/view/View;
    //   255: invokevirtual getTop : ()I
    //   258: istore #4
    //   260: aload_0
    //   261: getfield i : Landroid/view/View;
    //   264: invokevirtual getRight : ()I
    //   267: istore_3
    //   268: aload_0
    //   269: getfield i : Landroid/view/View;
    //   272: astore #9
    //   274: goto -> 203
    //   277: aload_0
    //   278: getfield a : Landroid/graphics/drawable/Drawable;
    //   281: iconst_0
    //   282: iconst_0
    //   283: iconst_0
    //   284: iconst_0
    //   285: invokevirtual setBounds : (IIII)V
    //   288: iconst_1
    //   289: istore_2
    //   290: aload_0
    //   291: iload_1
    //   292: putfield e : Z
    //   295: iload_1
    //   296: ifeq -> 339
    //   299: aload_0
    //   300: getfield b : Landroid/graphics/drawable/Drawable;
    //   303: ifnull -> 339
    //   306: aload_0
    //   307: getfield b : Landroid/graphics/drawable/Drawable;
    //   310: aload #6
    //   312: invokevirtual getLeft : ()I
    //   315: aload #6
    //   317: invokevirtual getTop : ()I
    //   320: aload #6
    //   322: invokevirtual getRight : ()I
    //   325: aload #6
    //   327: invokevirtual getBottom : ()I
    //   330: invokevirtual setBounds : (IIII)V
    //   333: iload #5
    //   335: istore_2
    //   336: goto -> 339
    //   339: iload_2
    //   340: ifeq -> 347
    //   343: aload_0
    //   344: invokevirtual invalidate : ()V
    //   347: return }
  
  public void onMeasure(int paramInt1, int paramInt2) { // Byte code:
    //   0: iload_2
    //   1: istore_3
    //   2: aload_0
    //   3: getfield h : Landroid/view/View;
    //   6: ifnonnull -> 46
    //   9: iload_2
    //   10: istore_3
    //   11: iload_2
    //   12: invokestatic getMode : (I)I
    //   15: ldc -2147483648
    //   17: if_icmpne -> 46
    //   20: iload_2
    //   21: istore_3
    //   22: aload_0
    //   23: getfield j : I
    //   26: iflt -> 46
    //   29: aload_0
    //   30: getfield j : I
    //   33: iload_2
    //   34: invokestatic getSize : (I)I
    //   37: invokestatic min : (II)I
    //   40: ldc -2147483648
    //   42: invokestatic makeMeasureSpec : (II)I
    //   45: istore_3
    //   46: aload_0
    //   47: iload_1
    //   48: iload_3
    //   49: invokespecial onMeasure : (II)V
    //   52: aload_0
    //   53: getfield h : Landroid/view/View;
    //   56: ifnonnull -> 60
    //   59: return
    //   60: iload_3
    //   61: invokestatic getMode : (I)I
    //   64: istore_2
    //   65: aload_0
    //   66: getfield g : Landroid/view/View;
    //   69: ifnull -> 178
    //   72: aload_0
    //   73: getfield g : Landroid/view/View;
    //   76: invokevirtual getVisibility : ()I
    //   79: bipush #8
    //   81: if_icmpeq -> 178
    //   84: iload_2
    //   85: ldc 1073741824
    //   87: if_icmpeq -> 178
    //   90: aload_0
    //   91: aload_0
    //   92: getfield h : Landroid/view/View;
    //   95: invokespecial a : (Landroid/view/View;)Z
    //   98: ifne -> 117
    //   101: aload_0
    //   102: getfield h : Landroid/view/View;
    //   105: astore #4
    //   107: aload_0
    //   108: aload #4
    //   110: invokespecial b : (Landroid/view/View;)I
    //   113: istore_1
    //   114: goto -> 139
    //   117: aload_0
    //   118: aload_0
    //   119: getfield i : Landroid/view/View;
    //   122: invokespecial a : (Landroid/view/View;)Z
    //   125: ifne -> 137
    //   128: aload_0
    //   129: getfield i : Landroid/view/View;
    //   132: astore #4
    //   134: goto -> 107
    //   137: iconst_0
    //   138: istore_1
    //   139: iload_2
    //   140: ldc -2147483648
    //   142: if_icmpne -> 153
    //   145: iload_3
    //   146: invokestatic getSize : (I)I
    //   149: istore_2
    //   150: goto -> 156
    //   153: ldc 2147483647
    //   155: istore_2
    //   156: aload_0
    //   157: aload_0
    //   158: invokevirtual getMeasuredWidth : ()I
    //   161: iload_1
    //   162: aload_0
    //   163: aload_0
    //   164: getfield g : Landroid/view/View;
    //   167: invokespecial b : (Landroid/view/View;)I
    //   170: iadd
    //   171: iload_2
    //   172: invokestatic min : (II)I
    //   175: invokevirtual setMeasuredDimension : (II)V
    //   178: return }
  
  public boolean onTouchEvent(MotionEvent paramMotionEvent) {
    super.onTouchEvent(paramMotionEvent);
    return true;
  }
  
  public void setPrimaryBackground(Drawable paramDrawable) { // Byte code:
    //   0: aload_0
    //   1: getfield a : Landroid/graphics/drawable/Drawable;
    //   4: ifnull -> 23
    //   7: aload_0
    //   8: getfield a : Landroid/graphics/drawable/Drawable;
    //   11: aconst_null
    //   12: invokevirtual setCallback : (Landroid/graphics/drawable/Drawable$Callback;)V
    //   15: aload_0
    //   16: aload_0
    //   17: getfield a : Landroid/graphics/drawable/Drawable;
    //   20: invokevirtual unscheduleDrawable : (Landroid/graphics/drawable/Drawable;)V
    //   23: aload_0
    //   24: aload_1
    //   25: putfield a : Landroid/graphics/drawable/Drawable;
    //   28: aload_1
    //   29: ifnull -> 79
    //   32: aload_1
    //   33: aload_0
    //   34: invokevirtual setCallback : (Landroid/graphics/drawable/Drawable$Callback;)V
    //   37: aload_0
    //   38: getfield h : Landroid/view/View;
    //   41: ifnull -> 79
    //   44: aload_0
    //   45: getfield a : Landroid/graphics/drawable/Drawable;
    //   48: aload_0
    //   49: getfield h : Landroid/view/View;
    //   52: invokevirtual getLeft : ()I
    //   55: aload_0
    //   56: getfield h : Landroid/view/View;
    //   59: invokevirtual getTop : ()I
    //   62: aload_0
    //   63: getfield h : Landroid/view/View;
    //   66: invokevirtual getRight : ()I
    //   69: aload_0
    //   70: getfield h : Landroid/view/View;
    //   73: invokevirtual getBottom : ()I
    //   76: invokevirtual setBounds : (IIII)V
    //   79: aload_0
    //   80: getfield d : Z
    //   83: istore_2
    //   84: iconst_0
    //   85: istore_3
    //   86: iload_2
    //   87: ifeq -> 104
    //   90: iload_3
    //   91: istore_2
    //   92: aload_0
    //   93: getfield c : Landroid/graphics/drawable/Drawable;
    //   96: ifnonnull -> 125
    //   99: iconst_1
    //   100: istore_2
    //   101: goto -> 125
    //   104: iload_3
    //   105: istore_2
    //   106: aload_0
    //   107: getfield a : Landroid/graphics/drawable/Drawable;
    //   110: ifnonnull -> 125
    //   113: iload_3
    //   114: istore_2
    //   115: aload_0
    //   116: getfield b : Landroid/graphics/drawable/Drawable;
    //   119: ifnonnull -> 125
    //   122: goto -> 99
    //   125: aload_0
    //   126: iload_2
    //   127: invokevirtual setWillNotDraw : (Z)V
    //   130: aload_0
    //   131: invokevirtual invalidate : ()V
    //   134: return }
  
  public void setSplitBackground(Drawable paramDrawable) { // Byte code:
    //   0: aload_0
    //   1: getfield c : Landroid/graphics/drawable/Drawable;
    //   4: ifnull -> 23
    //   7: aload_0
    //   8: getfield c : Landroid/graphics/drawable/Drawable;
    //   11: aconst_null
    //   12: invokevirtual setCallback : (Landroid/graphics/drawable/Drawable$Callback;)V
    //   15: aload_0
    //   16: aload_0
    //   17: getfield c : Landroid/graphics/drawable/Drawable;
    //   20: invokevirtual unscheduleDrawable : (Landroid/graphics/drawable/Drawable;)V
    //   23: aload_0
    //   24: aload_1
    //   25: putfield c : Landroid/graphics/drawable/Drawable;
    //   28: iconst_0
    //   29: istore_2
    //   30: aload_1
    //   31: ifnull -> 70
    //   34: aload_1
    //   35: aload_0
    //   36: invokevirtual setCallback : (Landroid/graphics/drawable/Drawable$Callback;)V
    //   39: aload_0
    //   40: getfield d : Z
    //   43: ifeq -> 70
    //   46: aload_0
    //   47: getfield c : Landroid/graphics/drawable/Drawable;
    //   50: ifnull -> 70
    //   53: aload_0
    //   54: getfield c : Landroid/graphics/drawable/Drawable;
    //   57: iconst_0
    //   58: iconst_0
    //   59: aload_0
    //   60: invokevirtual getMeasuredWidth : ()I
    //   63: aload_0
    //   64: invokevirtual getMeasuredHeight : ()I
    //   67: invokevirtual setBounds : (IIII)V
    //   70: aload_0
    //   71: getfield d : Z
    //   74: ifeq -> 91
    //   77: iload_2
    //   78: istore_3
    //   79: aload_0
    //   80: getfield c : Landroid/graphics/drawable/Drawable;
    //   83: ifnonnull -> 112
    //   86: iconst_1
    //   87: istore_3
    //   88: goto -> 112
    //   91: iload_2
    //   92: istore_3
    //   93: aload_0
    //   94: getfield a : Landroid/graphics/drawable/Drawable;
    //   97: ifnonnull -> 112
    //   100: iload_2
    //   101: istore_3
    //   102: aload_0
    //   103: getfield b : Landroid/graphics/drawable/Drawable;
    //   106: ifnonnull -> 112
    //   109: goto -> 86
    //   112: aload_0
    //   113: iload_3
    //   114: invokevirtual setWillNotDraw : (Z)V
    //   117: aload_0
    //   118: invokevirtual invalidate : ()V
    //   121: return }
  
  public void setStackedBackground(Drawable paramDrawable) { // Byte code:
    //   0: aload_0
    //   1: getfield b : Landroid/graphics/drawable/Drawable;
    //   4: ifnull -> 23
    //   7: aload_0
    //   8: getfield b : Landroid/graphics/drawable/Drawable;
    //   11: aconst_null
    //   12: invokevirtual setCallback : (Landroid/graphics/drawable/Drawable$Callback;)V
    //   15: aload_0
    //   16: aload_0
    //   17: getfield b : Landroid/graphics/drawable/Drawable;
    //   20: invokevirtual unscheduleDrawable : (Landroid/graphics/drawable/Drawable;)V
    //   23: aload_0
    //   24: aload_1
    //   25: putfield b : Landroid/graphics/drawable/Drawable;
    //   28: aload_1
    //   29: ifnull -> 86
    //   32: aload_1
    //   33: aload_0
    //   34: invokevirtual setCallback : (Landroid/graphics/drawable/Drawable$Callback;)V
    //   37: aload_0
    //   38: getfield e : Z
    //   41: ifeq -> 86
    //   44: aload_0
    //   45: getfield b : Landroid/graphics/drawable/Drawable;
    //   48: ifnull -> 86
    //   51: aload_0
    //   52: getfield b : Landroid/graphics/drawable/Drawable;
    //   55: aload_0
    //   56: getfield g : Landroid/view/View;
    //   59: invokevirtual getLeft : ()I
    //   62: aload_0
    //   63: getfield g : Landroid/view/View;
    //   66: invokevirtual getTop : ()I
    //   69: aload_0
    //   70: getfield g : Landroid/view/View;
    //   73: invokevirtual getRight : ()I
    //   76: aload_0
    //   77: getfield g : Landroid/view/View;
    //   80: invokevirtual getBottom : ()I
    //   83: invokevirtual setBounds : (IIII)V
    //   86: aload_0
    //   87: getfield d : Z
    //   90: istore_2
    //   91: iconst_0
    //   92: istore_3
    //   93: iload_2
    //   94: ifeq -> 111
    //   97: iload_3
    //   98: istore_2
    //   99: aload_0
    //   100: getfield c : Landroid/graphics/drawable/Drawable;
    //   103: ifnonnull -> 132
    //   106: iconst_1
    //   107: istore_2
    //   108: goto -> 132
    //   111: iload_3
    //   112: istore_2
    //   113: aload_0
    //   114: getfield a : Landroid/graphics/drawable/Drawable;
    //   117: ifnonnull -> 132
    //   120: iload_3
    //   121: istore_2
    //   122: aload_0
    //   123: getfield b : Landroid/graphics/drawable/Drawable;
    //   126: ifnonnull -> 132
    //   129: goto -> 106
    //   132: aload_0
    //   133: iload_2
    //   134: invokevirtual setWillNotDraw : (Z)V
    //   137: aload_0
    //   138: invokevirtual invalidate : ()V
    //   141: return }
  
  public void setTabContainer(ak paramak) {
    if (this.g != null)
      removeView(this.g); 
    this.g = paramak;
    if (paramak != null) {
      addView(paramak);
      ViewGroup.LayoutParams layoutParams = paramak.getLayoutParams();
      layoutParams.width = -1;
      layoutParams.height = -2;
      paramak.setAllowCollapse(false);
    } 
  }
  
  public void setTransitioning(boolean paramBoolean) {
    int k;
    this.f = paramBoolean;
    if (paramBoolean) {
      k = 393216;
    } else {
      k = 262144;
    } 
    setDescendantFocusability(k);
  }
  
  public void setVisibility(int paramInt) {
    boolean bool;
    super.setVisibility(paramInt);
    if (paramInt == 0) {
      bool = true;
    } else {
      bool = false;
    } 
    if (this.a != null)
      this.a.setVisible(bool, false); 
    if (this.b != null)
      this.b.setVisible(bool, false); 
    if (this.c != null)
      this.c.setVisible(bool, false); 
  }
  
  public ActionMode startActionModeForChild(View paramView, ActionMode.Callback paramCallback) { return null; }
  
  protected boolean verifyDrawable(Drawable paramDrawable) { return ((paramDrawable == this.a && !this.d) || (paramDrawable == this.b && this.e) || (paramDrawable == this.c && this.d) || super.verifyDrawable(paramDrawable)); }
}


/* Location:              /Users/dongbing/project/study-pen/android/05/classes-dex2jar.jar!/android/support/v7/widget/ActionBarContainer.class
 * Java compiler version: 6 (50.0)
 * JD-Core Version:       1.0.7
 */